{
  "app_name": "UTheme",
  "app_description": "Pobieranie Motywów",
  "menu": {
    "download_themes": "Pobierz Motywy",
    "download_themes_desc": "Pobierz motywy Wii U z internetu",
    "manage_themes": "Zarządzaj Motywami",
    "manage_themes_desc": "Zobacz i zarządzaj zainstalowanymi motywami",
    "settings": "Ustawienia",
    "settings_desc": "Konfiguruj źródła pobierania i inne opcje",
    "reboot": "Uruchom Ponownie System",
    "reboot_desc": "Uruchom ponownie konsolę Wii U",
    "about": "O UTheme",
    "about_desc": "Zobacz informacje o aplikacji i twórcach",
    "touch_hint": "Wskazówka: Obsługiwany ekran dotykowy!",
    "language_switch_hint": "Wskazówka: Możesz zmienić język w Ustawieniach"
  },
  "download": {
    "title": "Pobierz Motywy",
    "loading": "Ładowanie listy motywów...",
    "loading_cache": "Ładowanie pamięci podręcznej...",
    "loading_desc": "Proszę czekać...",
    "loading_image": "Ładowanie...",
    "themes_loaded": "motywów",
    "downloading": "Pobieranie motywu...",
    "download": "Pobierz",
    "refresh": "Odśwież",
    "theme_list": "Lista Motywów",
    "complete": "Pobieranie zakończone!",
    "error": "Wystąpił błąd",
    "no_themes": "Nie znaleziono motywów",
    "update_available": "Dostępna aktualizacja",
    "installed": "Pobrano",
    "local_install": "Instalacja lokalna",
    "search_hint": "Szukaj według nazwy, autora, tagów lub T+ID",
    "search_clear": "Wyczyść",
    "search_results": "wyników",
    "search_keyboard_hint": "Szukaj według nazwy, autora, tagów lub T+ID (np. T1, autor, tag)",
    "random_theme": "Losowy Motyw",
    "disk_space_low": "Niewystarczająca ilość miejsca ({space}MB). Wyczyść pamięć podręczną w Ustawieniach.",
    "disk_space_check_failed": "Nie można sprawdzić miejsca na dysku. Sprawdź kartę SD lub włącz logowanie."
  },
  "theme_detail": {
    "by": "Autor:",
    "updated": "Zaktualizowano:",
    "downloads": "pobrań",
    "likes": "polubień",
    "description": "Opis",
    "no_description": "Brak opisu",
    "tags": "Tagi",
    "download_theme": "Pobierz Motyw",
    "uninstall_theme": "Odinstaluj Motyw",
    "set_current_theme": "Ustaw jako Aktualny Motyw",
    "set_current_confirm": "Czy chcesz ustawić to jako nowy motyw menu Wii U?",
    "setting_current": "Ustawianie aktualnego motywu...",
    "set_current_complete": "Aktualny motyw zaktualizowany!",
    "set_current_error": "Nie udało się ustawić motywu!",
    "check_log": "Sprawdź dziennik: sd:/log/UTheme/utheme##.log",
    "uninstall_confirm": "Czy na pewno chcesz odinstalować ten motyw?",
    "uninstalling": "Odinstalowywanie motywu...",
    "uninstall_complete": "Odinstalowanie zakończone!",
    "downloading": "Pobieranie motywu...",
    "extracting": "Rozpakowywanie...",
    "installing": "Instalowanie motywu...",
    "complete": "Pobieranie zakończone!",
    "install_complete": "Instalacja zakończona!",
    "install_error": "Błąd instalacji",
    "error": "Błąd pobierania",
    "loading_preview": "Ładowanie podglądu...",
    "hints": "B: Powrót  |  A: Pobierz  |  <Arrow>: Zmień podgląd",
    "hints_local": "B: Powrót  |  A: Odinstaluj  | Y: Ustaw jako aktualny |  <Arrow>: Zmień podgląd",
    "preview_collage": "Kolaż",
    "preview_launcher": "Launcher",
    "preview_wara_wara": "Plac Wara Wara",
    "fullscreen_hint_switch": "<Arrow>: Przełącz",
    "fullscreen_hint_exit": "B / Dotknięcie: Wyjście"
  },
  "manage": {
    "title": "Zarządzaj Motywami",
    "description": "Zarządzaj zainstalowanymi motywami",
    "loading": "Skanowanie lokalnych motywów...",
    "loading_desc": "Proszę czekać...",
    "no_themes": "Brak zainstalowanych motywów",
    "download_first": "Najpierw pobierz kilka motywów",
    "go_download": "Naciśnij A, aby wrócić do menu głównego",
    "view_details": "Zobacz Szczegóły",
    "install": "Zainstaluj Motyw",
    "uninstall": "Odinstaluj Motyw",
    "installed": "Pobrano",
    "ready": "Gotowy",
    "current": "Aktualny Motyw",
    "developing": "Funkcja w opracowaniu",
    "install_local": "Zainstaluj Lokalny Motyw"
  },
  "local_install": {
    "title": "Zainstaluj Lokalny Motyw",
    "scanning": "Skanowanie plików .utheme...",
    "found_files": "Znaleziono plików motywów: {count}",
    "no_files": "Nie znaleziono plików .utheme",
    "path_hint": "Umieść pliki motywów w katalogu sd:/wiiu/themes/",
    "hints": "A: Zainstaluj  |  B: Powrót",
    "confirm_title": "Potwierdź Instalację Motywu",
    "delete_after_install": "Usuń oryginalny plik po instalacji",
    "confirm_hint": "A: Potwierdź instalację  |  X: Przełącz usuwanie  |  B: Anuluj",
    "install": "Zainstaluj",
    "installing": "Instalowanie motywu...",
    "install_complete": "Motyw pomyślnie zainstalowany!",
    "install_error": "Nie udało się zainstalować motywu"
  },
  "settings": {
    "title": "Ustawienia",
    "description": "Ustawienia aplikacji",
    "language": "Język",
    "language_desc": "Wybierz język interfejsu",
    "download_path": "Ścieżka Pobierania",
    "download_path_desc": "Lokalizacja zapisu pobranych motywów",
    "auto_install": "Automatyczna Instalacja",
    "auto_install_desc": "Automatycznie instaluj motywy po pobraniu",
    "bgm_enabled": "Muzyka w Tle",
    "bgm_enabled_desc": "Odtwarzaj muzykę w tle",
    "bgm_download": "Pobierz BGM",
    "bgm_download_desc": "Pobierz muzykę w tle z internetu",
    "bgm_url": "URL BGM",
    "bgm_url_desc": "Adres pobierania muzyki w tle",
    "logging": "Włącz Dziennik",
    "logging_desc": "Rejestruj dziennik działania aplikacji",
    "verbose_logging": "Szczegółowy Dziennik",
    "verbose_logging_desc": "Rejestruj bardziej szczegółowe informacje debugowania",
    "clear_cache": "Wyczyść Pamięć Podręczną",
    "clear_cache_desc": "Usuń wszystkie dane pamięci podręcznej i pliki konfiguracyjne",
    "press_to_clear": "Naciśnij A, aby wyczyścić",
    "cache_cleared": "Pamięć podręczna wyczyszczona",
    "restarting_app": "Zamykanie programu...",
    "developing": "Funkcja w opracowaniu"
  },
  "reboot": {
    "title": "Uruchom Ponownie System",
    "confirm": "Czy na pewno chcesz uruchomić ponownie system?",
    "confirm_button": "Uruchom Ponownie",
    "press_a": "Potwierdź ponowne uruchomienie",
    "press_b": "Anuluj"
  },
  "about": {
    "title": "O Programie",
    "credits": "Twórcy",
    "fonts": "Czcionki",
    "source_code": "Kod Źródłowy",
    "based_on": "Oparte na następujących projektach:",
    "system_font": "Czcionka Systemu Wii U",
    "fontawesome": "FontAwesome (ikony)",
    "terminus": "Terminus Font (monospace)",
    "lingobrew": "LingoBrew - Główna funkcjonalność",
    "themiify": "Themiify - Łatki i instalacja",
    "wiiuident": "WiiUIdent - Framework GUI",
    "haxcopy": "haxcopy - Dodatkowa funkcjonalność",
    "themezer": "Themezer - Dostawca API",
    "libraries": "Biblioteki i Narzędzia",
    "libwebp": "libwebp - Dekodowanie obrazów",
    "minizip": "MiniZIP - Obsługa archiwów",
    "hips": "Hips - System łatek",
    "rapidjson": "RapidJSON - Parsowanie JSON",
    "nathaniel": "Nathaniel - Ulepszenia łatek i integracja StyleMiiu"
  },
  "common": {
    "initializing": "Inicjalizacja...",
    "loading": "Ładowanie...",
    "ok": "OK",
    "cancel": "Anuluj",
    "back": "Powrót",
    "exit": "Wyjście",
    "select": "Wybierz",
    "confirm": "Potwierdź",
    "error": "Błąd",
    "warning": "Ostrzeżenie",
    "success": "Sukces",
    "failed": "Niepowodzenie",
    "yes": "Tak",
    "no": "Nie",
    "local_mode": "Tryb Lokalny",
    "mocha_unavailable": "Mocha niedostępna, nie można zainstalować/odinstalować motywów",
    "other_features_available": "Inne funkcje dostępne",
    "press_a_continue": "Naciśnij A, aby kontynuować",
    "init_mocha": "Inicjalizacja Mocha...",
    "filesystem_error": "Błąd systemu plików",
    "mount_filesystem": "Montowanie systemu plików...",
    "load_complete": "Ładowanie zakończone!",
    "bgm_downloading": "Pobieranie BGM...",
    "bgm_download_complete": "Pobieranie BGM zakończone!",
    "bgm_download_error": "Błąd pobierania BGM",
    "bgm_reloaded": "BGM przeładowany"
  },
  "input": {
    "select": "Wybierz",
    "confirm": "Potwierdź", 
    "back": "Powrót",
    "exit": "Wyjście"
  }
}
